3rd Sem/DDCO Lab/Week 3/4bit.v
module fulladdR(input wire a,b,cin,output wire sum,cout);
	wire t;
	assign t = a^b;
	assign sum = t^cin;
	assign cout = (a&b)|(b&cin)|(a&cin);
endmodule


module r_c_addr(input wire [3:0] a,input wire [3:0]b, input wire cin, output wire [3:0] s, output wire cout);
	wire [2:0]c;
	fulladdR f_0(a0,b0,cin,s0,c0);
	fulladdR f_1(a1,b1,c0,s1,c1);
	fulladdR f_2(a2,b2,c1,s2,c2);
	fulladdR f_3(a3,b3,c2,s3,cout);
endmodule

3rd Sem/DDCO Lab/Week 3/dtestBench.v
`timescale 1 ns / 100 ps
`define TESTVECS 8

module tb;
  reg clk, reset;
  reg [3:0] i0, i1; reg cin;
  wire [3:0] o; wire cout;
  reg [8:0] test_vecs [0:(`TESTVECS-1)];
  integer i;
  initial begin $dumpfile("dump.vcd");
 $dumpvars(0,tb); 
  end
  initial begin reset = 1'b1; #12.5 reset = 1'b0; end
  initial clk = 1'b0; always #5 clk =~ clk;
  initial begin
    test_vecs[0] = 9'b000000010;
    test_vecs[1] = 9'b000100010;
    test_vecs[2] = 9'b011100010;
    test_vecs[3] = 9'b000001110;
    test_vecs[4] = 9'b011001111;
    test_vecs[5] = 9'b001110011;
    test_vecs[6] = 9'b111100011;
    test_vecs[7] = 9'b011101110;
  end
  initial {i0, i1, cin, i} = 0;
  r_c_addr u0 (i0, i1, cin, o, cout);
  initial begin
    #6 for(i=0;i<`TESTVECS;i=i+1)
      begin #10 {i0, i1, cin}=test_vecs[i]; end
    #100 $finish;
  end
endmodule

3rd Sem/DDCO Lab/Week 3/dump.vcd
$date
	Tue Sep 21 09:00:22 2021
$end
$version
	Icarus Verilog
$end
$timescale
	100ps
$end
$scope module tb $end
$var wire 1 ! cout $end
$var wire 4 " o [3:0] $end
$var reg 1 # cin $end
$var reg 1 $ clk $end
$var integer 32 % i [31:0] $end
$var reg 4 & i0 [3:0] $end
$var reg 4 ' i1 [3:0] $end
$var reg 1 ( reset $end
$scope module u0 $end
$var wire 4 ) a [3:0] $end
$var wire 1 * a0 $end
$var wire 1 + a1 $end
$var wire 1 , a2 $end
$var wire 1 - a3 $end
$var wire 4 . b [3:0] $end
$var wire 1 / b0 $end
$var wire 1 0 b1 $end
$var wire 1 1 b2 $end
$var wire 1 2 b3 $end
$var wire 1 3 c0 $end
$var wire 1 4 c1 $end
$var wire 1 5 c2 $end
$var wire 1 6 cin $end
$var wire 1 ! cout $end
$var wire 4 7 s [3:0] $end
$var wire 1 8 s0 $end
$var wire 1 9 s1 $end
$var wire 1 : s2 $end
$var wire 1 ; s3 $end
$scope module f_0 $end
$var wire 1 * a $end
$var wire 1 / b $end
$var wire 1 6 cin $end
$var wire 1 3 cout $end
$var wire 1 8 sum $end
$var wire 1 < t $end
$upscope $end
$scope module f_1 $end
$var wire 1 + a $end
$var wire 1 0 b $end
$var wire 1 3 cin $end
$var wire 1 4 cout $end
$var wire 1 9 sum $end
$var wire 1 = t $end
$upscope $end
$scope module f_2 $end
$var wire 1 , a $end
$var wire 1 1 b $end
$var wire 1 4 cin $end
$var wire 1 5 cout $end
$var wire 1 : sum $end
$var wire 1 > t $end
$upscope $end
$scope module f_3 $end
$var wire 1 - a $end
$var wire 1 2 b $end
$var wire 1 5 cin $end
$var wire 1 ! cout $end
$var wire 1 ; sum $end
$var wire 1 ? t $end
$upscope $end
$upscope $end
$upscope $end
$enddefinitions $end
#0
$dumpvars
x?
x>
x=
x<
x;
x:
x9
x8
bz 7
06
x5
x4
x3
z2
z1
z0
z/
b0 .
z-
z,
z+
z*
b0 )
1(
b0 '
b0 &
b0 %
0$
0#
bz "
x!
$end
#50
1$
#100
0$
#125
0(
#150
1$
#160
b1 %
b1 '
b1 .
#200
0$
#250
1$
#260
b10 %
b1 &
b1 )
#300
0$
#350
1$
#360
b11 %
b111 &
b111 )
#400
0$
#450
1$
#460
b100 %
b0 &
b0 )
b111 '
b111 .
#500
0$
#550
1$
#560
b101 %
b110 &
b110 )
1#
16
#600
0$
#650
1$
#660
b110 %
b11 &
b11 )
b1001 '
b1001 .
#700
0$
#750
1$
#760
b111 %
b1111 &
b1111 )
b1 '
b1 .
#800
0$
#850
1$
#860
b1000 %
b111 &
b111 )
b111 '
b111 .
0#
06
