3rd Sem/DDCO Lab/Week 4/alu_slice.v
module full_adder(input wire a, b, cin,output wire cout, sum);
	assign sum = a^b^cin;
	assign cout = (b&cin)|(a&cin)|(a&b);
endmodule

module xor2 (input wire i0, i1, output wire o);
  assign o = i0 ^ i1;
endmodule

module and2 (input wire i0, i1, output wire o);
  assign o = i0 & i1;
endmodule

module or2 (input wire i0, i1, output wire o);
  assign o = i0 | i1;
endmodule

module mux2 (input wire i0, i1, j, output wire o);
  assign o = (j==0)?i0:i1;
endmodule

module alu_slice(input wire cin,i0,i1,input wire [1:0]op,output wire o,cout);
	wire temp,o1,o2,o3,o4;
	
	xor2 x(i1,op[0],temp);
	full_adder f(i0,temp,cin,cout,o1);

	and2 a(i0,i1,o2);
	or2 orr(i0,i1,o3);

	mux2 m1(o2,o3,op[0],o4);
	mux2 m2(o1,o4,op[1],o);
endmodule

3rd Sem/DDCO Lab/Week 4/alu.v
module alu (input wire [1:0] op, input wire [15:0] i0, i1,output wire [15:0] o, output wire cout);
	wire [14:0]c;

	alu_slice a0(op[0],i0[0],i1[0],op,o[0],c[0]);
	alu_slice a1(c[0],i0[1],i1[1],op,o[1],c[1]);
	alu_slice a2(c[1],i0[2],i1[2],op,o[2],c[2]);
	alu_slice a3(c[2],i0[3],i1[3],op,o[3],c[3]);
	alu_slice a4(c[3],i0[4],i1[4],op,o[4],c[4]);
	alu_slice a5(c[4],i0[5],i1[5],op,o[5],c[5]);
	alu_slice a6(c[5],i0[6],i1[6],op,o[6],c[6]);
	alu_slice a7(c[6],i0[7],i1[7],op,o[7],c[7]);
	alu_slice a8(c[7],i0[8],i1[8],op,o[8],c[8]);
	alu_slice a9(c[8],i0[9],i1[9],op,o[9],c[9]);
	alu_slice a10(c[9],i0[10],i1[10],op,o[10],c[10]);
	alu_slice a11(c[10],i0[11],i1[11],op,o[11],c[11]);
	alu_slice a12(c[11],i0[12],i1[12],op,o[12],c[12]);
	alu_slice a13(c[12],i0[13],i1[13],op,o[13],c[13]);
	alu_slice a14(c[13],i0[14],i1[14],op,o[14],c[14]);
	alu_slice a15(c[14],i0[15],i1[15],op,o[15],cout);
endmodule

3rd Sem/DDCO Lab/Week 4/tb_alu.v
`timescale 1 ns / 100 ps
`define TESTVECS 16

module tb;
  reg clk, reset;
  reg [1:0] op; reg [15:0] i0, i1;
  wire [15:0] o; wire cout;
  reg [33:0] test_vecs [0:(`TESTVECS-1)];
  integer i;
  initial begin $dumpfile("dump.vcd"); $dumpvars(0,tb); end
  initial begin reset = 1'b1; #12.5 reset = 1'b0; end
  initial clk = 1'b0; always #5 clk =~ clk;
  initial begin
    test_vecs[0][33:32] = 2'b00; test_vecs[0][31:16] = 16'h0000;test_vecs[0][15:0] = 16'h0000;
    test_vecs[1][33:32] = 2'b00; test_vecs[1][31:16] = 16'haa55;test_vecs[1][15:0] = 16'h55aa;
    test_vecs[2][33:32] = 2'b00; test_vecs[2][31:16] = 16'hffff;test_vecs[2][15:0] = 16'h0001;
    test_vecs[3][33:32] = 2'b00; test_vecs[3][31:16] = 16'h0001;test_vecs[3][15:0] = 16'h7fff;
    test_vecs[4][33:32] = 2'b01; test_vecs[4][31:16] = 16'h0000;test_vecs[4][15:0] = 16'h0000;
    test_vecs[5][33:32] = 2'b01; test_vecs[5][31:16] = 16'haa55;test_vecs[5][15:0] = 16'h55aa;
    test_vecs[6][33:32] = 2'b01; test_vecs[6][31:16] = 16'hffff;test_vecs[6][15:0] = 16'h0001;
    test_vecs[7][33:32] = 2'b01; test_vecs[7][31:16] = 16'h0001;test_vecs[7][15:0] = 16'h7fff;
    test_vecs[8][33:32] = 2'b10; test_vecs[8][31:16] = 16'h0000;test_vecs[8][15:0] = 16'h0000;
    test_vecs[9][33:32] = 2'b10; test_vecs[9][31:16] = 16'haa55;test_vecs[9][15:0] = 16'h55aa;
    test_vecs[10][33:32] = 2'b10; test_vecs[10][31:16] = 16'hffff;test_vecs[10][15:0] = 16'h0001;
    test_vecs[11][33:32] = 2'b10; test_vecs[11][31:16] = 16'h0001;test_vecs[11][15:0] = 16'h7fff;
    test_vecs[12][33:32] = 2'b11; test_vecs[12][31:16] = 16'h0000;test_vecs[12][15:0] = 16'h0000;
    test_vecs[13][33:32] = 2'b11; test_vecs[13][31:16] = 16'haa55;test_vecs[13][15:0] = 16'h55aa;
    test_vecs[14][33:32] = 2'b11; test_vecs[14][31:16] = 16'hffff;test_vecs[14][15:0] = 16'h0001;
    test_vecs[15][33:32] = 2'b11; test_vecs[15][31:16] = 16'h0001;test_vecs[15][15:0] = 16'h7fff;
  end
  initial {op, i0, i1} = 0;
  alu alu_0 (op, i0, i1, o, cout);
  initial begin
    #6 for(i=0;i<`TESTVECS;i=i+1)
      begin #10 {op, i0, i1}=test_vecs[i]; end
    #100 $finish;
  end
endmodule

3rd Sem/DDCO Lab/Week 4/dump.vcd
$date
	Tue Sep 21 08:26:30 2021
$end
$version
	Icarus Verilog
$end
$timescale
	100ps
$end
$scope module tb $end
$var wire 1 ! cout $end
$var wire 16 " o [15:0] $end
$var reg 1 # clk $end
$var integer 32 $ i [31:0] $end
$var reg 16 % i0 [15:0] $end
$var reg 16 & i1 [15:0] $end
$var reg 2 ' op [1:0] $end
$var reg 1 ( reset $end
$scope module alu_0 $end
$var wire 15 ) c [14:0] $end
$var wire 1 ! cout $end
$var wire 16 * i0 [15:0] $end
$var wire 16 + i1 [15:0] $end
$var wire 16 , o [15:0] $end
$var wire 2 - op [1:0] $end
$scope module a0 $end
$var wire 1 . cin $end
$var wire 1 / cout $end
$var wire 1 0 i0 $end
$var wire 1 1 i1 $end
$var wire 1 2 o $end
$var wire 1 3 o1 $end
$var wire 1 4 o2 $end
$var wire 1 5 o3 $end
$var wire 1 6 o4 $end
$var wire 2 7 op [1:0] $end
$var wire 1 8 temp $end
$scope module x $end
$var wire 1 1 i0 $end
$var wire 1 9 i1 $end
$var wire 1 8 o $end
$upscope $end
$scope module f $end
$var wire 1 0 a $end
$var wire 1 8 b $end
$var wire 1 . cin $end
$var wire 1 / cout $end
$var wire 1 3 sum $end
$upscope $end
$scope module a $end
$var wire 1 0 i0 $end
$var wire 1 1 i1 $end
$var wire 1 4 o $end
$upscope $end
$scope module orr $end
$var wire 1 0 i0 $end
$var wire 1 1 i1 $end
$var wire 1 5 o $end
$upscope $end
$scope module m1 $end
$var wire 1 4 i0 $end
$var wire 1 5 i1 $end
$var wire 1 : j $end
$var wire 1 6 o $end
$upscope $end
$scope module m2 $end
$var wire 1 3 i0 $end
$var wire 1 6 i1 $end
$var wire 1 ; j $end
$var wire 1 2 o $end
$upscope $end
$upscope $end
$scope module a1 $end
$var wire 1 < cin $end
$var wire 1 = cout $end
$var wire 1 > i0 $end
$var wire 1 ? i1 $end
$var wire 1 @ o $end
$var wire 1 A o1 $end
$var wire 1 B o2 $end
$var wire 1 C o3 $end
$var wire 1 D o4 $end
$var wire 2 E op [1:0] $end
$var wire 1 F temp $end
$scope module x $end
$var wire 1 ? i0 $end
$var wire 1 G i1 $end
$var wire 1 F o $end
$upscope $end
$scope module f $end
$var wire 1 > a $end
$var wire 1 F b $end
$var wire 1 < cin $end
$var wire 1 = cout $end
$var wire 1 A sum $end
$upscope $end
$scope module a $end
$var wire 1 > i0 $end
$var wire 1 ? i1 $end
$var wire 1 B o $end
$upscope $end
$scope module orr $end
$var wire 1 > i0 $end
$var wire 1 ? i1 $end
$var wire 1 C o $end
$upscope $end
$scope module m1 $end
$var wire 1 B i0 $end
$var wire 1 C i1 $end
$var wire 1 H j $end
$var wire 1 D o $end
$upscope $end
$scope module m2 $end
$var wire 1 A i0 $end
$var wire 1 D i1 $end
$var wire 1 I j $end
$var wire 1 @ o $end
$upscope $end
$upscope $end
$scope module a2 $end
$var wire 1 J cin $end
$var wire 1 K cout $end
$var wire 1 L i0 $end
$var wire 1 M i1 $end
$var wire 1 N o $end
$var wire 1 O o1 $end
$var wire 1 P o2 $end
$var wire 1 Q o3 $end
$var wire 1 R o4 $end
$var wire 2 S op [1:0] $end
$var wire 1 T temp $end
$scope module x $end
$var wire 1 M i0 $end
$var wire 1 U i1 $end
$var wire 1 T o $end
$upscope $end
$scope module f $end
$var wire 1 L a $end
$var wire 1 T b $end
$var wire 1 J cin $end
$var wire 1 K cout $end
$var wire 1 O sum $end
$upscope $end
$scope module a $end
$var wire 1 L i0 $end
$var wire 1 M i1 $end
$var wire 1 P o $end
$upscope $end
$scope module orr $end
$var wire 1 L i0 $end
$var wire 1 M i1 $end
$var wire 1 Q o $end
$upscope $end
$scope module m1 $end
$var wire 1 P i0 $end
$var wire 1 Q i1 $end
$var wire 1 V j $end
$var wire 1 R o $end
$upscope $end
$scope module m2 $end
$var wire 1 O i0 $end
$var wire 1 R i1 $end
$var wire 1 W j $end
$var wire 1 N o $end
$upscope $end
$upscope $end
$scope module a3 $end
$var wire 1 X cin $end
$var wire 1 Y cout $end
$var wire 1 Z i0 $end
$var wire 1 [ i1 $end
$var wire 1 \ o $end
$var wire 1 ] o1 $end
$var wire 1 ^ o2 $end
$var wire 1 _ o3 $end
$var wire 1 ` o4 $end
$var wire 2 a op [1:0] $end
$var wire 1 b temp $end
$scope module x $end
$var wire 1 [ i0 $end
$var wire 1 c i1 $end
$var wire 1 b o $end
$upscope $end
$scope module f $end
$var wire 1 Z a $end
$var wire 1 b b $end
$var wire 1 X cin $end
$var wire 1 Y cout $end
$var wire 1 ] sum $end
$upscope $end
$scope module a $end
$var wire 1 Z i0 $end
$var wire 1 [ i1 $end
$var wire 1 ^ o $end
$upscope $end
$scope module orr $end
$var wire 1 Z i0 $end
$var wire 1 [ i1 $end
$var wire 1 _ o $end
$upscope $end
$scope module m1 $end
$var wire 1 ^ i0 $end
$var wire 1 _ i1 $end
$var wire 1 d j $end
$var wire 1 ` o $end
$upscope $end
$scope module m2 $end
$var wire 1 ] i0 $end
$var wire 1 ` i1 $end
$var wire 1 e j $end
$var wire 1 \ o $end
$upscope $end
$upscope $end
$scope module a4 $end
$var wire 1 f cin $end
$var wire 1 g cout $end
$var wire 1 h i0 $end
$var wire 1 i i1 $end
$var wire 1 j o $end
$var wire 1 k o1 $end
$var wire 1 l o2 $end
$var wire 1 m o3 $end
$var wire 1 n o4 $end
$var wire 2 o op [1:0] $end
$var wire 1 p temp $end
$scope module x $end
$var wire 1 i i0 $end
$var wire 1 q i1 $end
$var wire 1 p o $end
$upscope $end
$scope module f $end
$var wire 1 h a $end
$var wire 1 p b $end
$var wire 1 f cin $end
$var wire 1 g cout $end
$var wire 1 k sum $end
$upscope $end
$scope module a $end
$var wire 1 h i0 $end
$var wire 1 i i1 $end
$var wire 1 l o $end
$upscope $end
$scope module orr $end
$var wire 1 h i0 $end
$var wire 1 i i1 $end
$var wire 1 m o $end
$upscope $end
$scope module m1 $end
$var wire 1 l i0 $end
$var wire 1 m i1 $end
$var wire 1 r j $end
$var wire 1 n o $end
$upscope $end
$scope module m2 $end
$var wire 1 k i0 $end
$var wire 1 n i1 $end
$var wire 1 s j $end
$var wire 1 j o $end
$upscope $end
$upscope $end
$scope module a5 $end
$var wire 1 t cin $end
$var wire 1 u cout $end
$var wire 1 v i0 $end
$var wire 1 w i1 $end
$var wire 1 x o $end
$var wire 1 y o1 $end
$var wire 1 z o2 $end
$var wire 1 { o3 $end
$var wire 1 | o4 $end
$var wire 2 } op [1:0] $end
$var wire 1 ~ temp $end
$scope module x $end
$var wire 1 w i0 $end
$var wire 1 !" i1 $end
$var wire 1 ~ o $end
$upscope $end
$scope module f $end
$var wire 1 v a $end
$var wire 1 ~ b $end
$var wire 1 t cin $end
$var wire 1 u cout $end
$var wire 1 y sum $end
$upscope $end
$scope module a $end
$var wire 1 v i0 $end
$var wire 1 w i1 $end
$var wire 1 z o $end
$upscope $end
$scope module orr $end
$var wire 1 v i0 $end
$var wire 1 w i1 $end
$var wire 1 { o $end
$upscope $end
$scope module m1 $end
$var wire 1 z i0 $end
$var wire 1 { i1 $end
$var wire 1 "" j $end
$var wire 1 | o $end
$upscope $end
$scope module m2 $end
$var wire 1 y i0 $end
$var wire 1 | i1 $end
$var wire 1 #" j $end
$var wire 1 x o $end
$upscope $end
$upscope $end
$scope module a6 $end
$var wire 1 $" cin $end
$var wire 1 %" cout $end
$var wire 1 &" i0 $end
$var wire 1 '" i1 $end
$var wire 1 (" o $end
$var wire 1 )" o1 $end
$var wire 1 *" o2 $end
$var wire 1 +" o3 $end
$var wire 1 ," o4 $end
$var wire 2 -" op [1:0] $end
$var wire 1 ." temp $end
$scope module x $end
$var wire 1 '" i0 $end
$var wire 1 /" i1 $end
$var wire 1 ." o $end
$upscope $end
$scope module f $end
$var wire 1 &" a $end
$var wire 1 ." b $end
$var wire 1 $" cin $end
$var wire 1 %" cout $end
$var wire 1 )" sum $end
$upscope $end
$scope module a $end
$var wire 1 &" i0 $end
$var wire 1 '" i1 $end
$var wire 1 *" o $end
$upscope $end
$scope module orr $end
$var wire 1 &" i0 $end
$var wire 1 '" i1 $end
$var wire 1 +" o $end
$upscope $end
$scope module m1 $end
$var wire 1 *" i0 $end
$var wire 1 +" i1 $end
$var wire 1 0" j $end
$var wire 1 ," o $end
$upscope $end
$scope module m2 $end
$var wire 1 )" i0 $end
$var wire 1 ," i1 $end
$var wire 1 1" j $end
$var wire 1 (" o $end
$upscope $end
$upscope $end
$scope module a7 $end
$var wire 1 2" cin $end
$var wire 1 3" cout $end
$var wire 1 4" i0 $end
$var wire 1 5" i1 $end
$var wire 1 6" o $end
$var wire 1 7" o1 $end
$var wire 1 8" o2 $end
$var wire 1 9" o3 $end
$var wire 1 :" o4 $end
$var wire 2 ;" op [1:0] $end
$var wire 1 <" temp $end
$scope module x $end
$var wire 1 5" i0 $end
$var wire 1 =" i1 $end
$var wire 1 <" o $end
$upscope $end
$scope module f $end
$var wire 1 4" a $end
$var wire 1 <" b $end
$var wire 1 2" cin $end
$var wire 1 3" cout $end
$var wire 1 7" sum $end
$upscope $end
$scope module a $end
$var wire 1 4" i0 $end
$var wire 1 5" i1 $end
$var wire 1 8" o $end
$upscope $end
$scope module orr $end
$var wire 1 4" i0 $end
$var wire 1 5" i1 $end
$var wire 1 9" o $end
$upscope $end
$scope module m1 $end
$var wire 1 8" i0 $end
$var wire 1 9" i1 $end
$var wire 1 >" j $end
$var wire 1 :" o $end
$upscope $end
$scope module m2 $end
$var wire 1 7" i0 $end
$var wire 1 :" i1 $end
$var wire 1 ?" j $end
$var wire 1 6" o $end
$upscope $end
$upscope $end
$scope module a8 $end
$var wire 1 @" cin $end
$var wire 1 A" cout $end
$var wire 1 B" i0 $end
$var wire 1 C" i1 $end
$var wire 1 D" o $end
$var wire 1 E" o1 $end
$var wire 1 F" o2 $end
$var wire 1 G" o3 $end
$var wire 1 H" o4 $end
$var wire 2 I" op [1:0] $end
$var wire 1 J" temp $end
$scope module x $end
$var wire 1 C" i0 $end
$var wire 1 K" i1 $end
$var wire 1 J" o $end
$upscope $end
$scope module f $end
$var wire 1 B" a $end
$var wire 1 J" b $end
$var wire 1 @" cin $end
$var wire 1 A" cout $end
$var wire 1 E" sum $end
$upscope $end
$scope module a $end
$var wire 1 B" i0 $end
$var wire 1 C" i1 $end
$var wire 1 F" o $end
$upscope $end
$scope module orr $end
$var wire 1 B" i0 $end
$var wire 1 C" i1 $end
$var wire 1 G" o $end
$upscope $end
$scope module m1 $end
$var wire 1 F" i0 $end
$var wire 1 G" i1 $end
$var wire 1 L" j $end
$var wire 1 H" o $end
$upscope $end
$scope module m2 $end
$var wire 1 E" i0 $end
$var wire 1 H" i1 $end
$var wire 1 M" j $end
$var wire 1 D" o $end
$upscope $end
$upscope $end
$scope module a9 $end
$var wire 1 N" cin $end
$var wire 1 O" cout $end
$var wire 1 P" i0 $end
$var wire 1 Q" i1 $end
$var wire 1 R" o $end
$var wire 1 S" o1 $end
$var wire 1 T" o2 $end
$var wire 1 U" o3 $end
$var wire 1 V" o4 $end
$var wire 2 W" op [1:0] $end
$var wire 1 X" temp $end
$scope module x $end
$var wire 1 Q" i0 $end
$var wire 1 Y" i1 $end
$var wire 1 X" o $end
$upscope $end
$scope module f $end
$var wire 1 P" a $end
$var wire 1 X" b $end
$var wire 1 N" cin $end
$var wire 1 O" cout $end
$var wire 1 S" sum $end
$upscope $end
$scope module a $end
$var wire 1 P" i0 $end
$var wire 1 Q" i1 $end
$var wire 1 T" o $end
$upscope $end
$scope module orr $end
$var wire 1 P" i0 $end
$var wire 1 Q" i1 $end
$var wire 1 U" o $end
$upscope $end
$scope module m1 $end
$var wire 1 T" i0 $end
$var wire 1 U" i1 $end
$var wire 1 Z" j $end
$var wire 1 V" o $end
$upscope $end
$scope module m2 $end
$var wire 1 S" i0 $end
$var wire 1 V" i1 $end
$var wire 1 [" j $end
$var wire 1 R" o $end
$upscope $end
$upscope $end
$scope module a10 $end
$var wire 1 \" cin $end
$var wire 1 ]" cout $end
$var wire 1 ^" i0 $end
$var wire 1 _" i1 $end
$var wire 1 `" o $end
$var wire 1 a" o1 $end
$var wire 1 b" o2 $end
$var wire 1 c" o3 $end
$var wire 1 d" o4 $end
$var wire 2 e" op [1:0] $end
$var wire 1 f" temp $end
$scope module x $end
$var wire 1 _" i0 $end
$var wire 1 g" i1 $end
$var wire 1 f" o $end
$upscope $end
$scope module f $end
$var wire 1 ^" a $end
$var wire 1 f" b $end
$var wire 1 \" cin $end
$var wire 1 ]" cout $end
$var wire 1 a" sum $end
$upscope $end
$scope module a $end
$var wire 1 ^" i0 $end
$var wire 1 _" i1 $end
$var wire 1 b" o $end
$upscope $end
$scope module orr $end
$var wire 1 ^" i0 $end
$var wire 1 _" i1 $end
$var wire 1 c" o $end
$upscope $end
$scope module m1 $end
$var wire 1 b" i0 $end
$var wire 1 c" i1 $end
$var wire 1 h" j $end
$var wire 1 d" o $end
$upscope $end
$scope module m2 $end
$var wire 1 a" i0 $end
$var wire 1 d" i1 $end
$var wire 1 i" j $end
$var wire 1 `" o $end
$upscope $end
$upscope $end
$scope module a11 $end
$var wire 1 j" cin $end
$var wire 1 k" cout $end
$var wire 1 l" i0 $end
$var wire 1 m" i1 $end
$var wire 1 n" o $end
$var wire 1 o" o1 $end
$var wire 1 p" o2 $end
$var wire 1 q" o3 $end
$var wire 1 r" o4 $end
$var wire 2 s" op [1:0] $end
$var wire 1 t" temp $end
$scope module x $end
$var wire 1 m" i0 $end
$var wire 1 u" i1 $end
$var wire 1 t" o $end
$upscope $end
$scope module f $end
$var wire 1 l" a $end
$var wire 1 t" b $end
$var wire 1 j" cin $end
$var wire 1 k" cout $end
$var wire 1 o" sum $end
$upscope $end
$scope module a $end
$var wire 1 l" i0 $end
$var wire 1 m" i1 $end
$var wire 1 p" o $end
$upscope $end
$scope module orr $end
$var wire 1 l" i0 $end
$var wire 1 m" i1 $end
$var wire 1 q" o $end
$upscope $end
$scope module m1 $end
$var wire 1 p" i0 $end
$var wire 1 q" i1 $end
$var wire 1 v" j $end
$var wire 1 r" o $end
$upscope $end
$scope module m2 $end
$var wire 1 o" i0 $end
$var wire 1 r" i1 $end
$var wire 1 w" j $end
$var wire 1 n" o $end
$upscope $end
$upscope $end
$scope module a12 $end
$var wire 1 x" cin $end
$var wire 1 y" cout $end
$var wire 1 z" i0 $end
$var wire 1 {" i1 $end
$var wire 1 |" o $end
$var wire 1 }" o1 $end
$var wire 1 ~" o2 $end
$var wire 1 !# o3 $end
$var wire 1 "# o4 $end
$var wire 2 ## op [1:0] $end
$var wire 1 $# temp $end
$scope module x $end
$var wire 1 {" i0 $end
$var wire 1 %# i1 $end
$var wire 1 $# o $end
$upscope $end
$scope module f $end
$var wire 1 z" a $end
$var wire 1 $# b $end
$var wire 1 x" cin $end
$var wire 1 y" cout $end
$var wire 1 }" sum $end
$upscope $end
$scope module a $end
$var wire 1 z" i0 $end
$var wire 1 {" i1 $end
$var wire 1 ~" o $end
$upscope $end
$scope module orr $end
$var wire 1 z" i0 $end
$var wire 1 {" i1 $end
$var wire 1 !# o $end
$upscope $end
$scope module m1 $end
$var wire 1 ~" i0 $end
$var wire 1 !# i1 $end
$var wire 1 &# j $end
$var wire 1 "# o $end
$upscope $end
$scope module m2 $end
$var wire 1 }" i0 $end
$var wire 1 "# i1 $end
$var wire 1 '# j $end
$var wire 1 |" o $end
$upscope $end
$upscope $end
$scope module a13 $end
$var wire 1 (# cin $end
$var wire 1 )# cout $end
$var wire 1 *# i0 $end
$var wire 1 +# i1 $end
$var wire 1 ,# o $end
$var wire 1 -# o1 $end
$var wire 1 .# o2 $end
$var wire 1 /# o3 $end
$var wire 1 0# o4 $end
$var wire 2 1# op [1:0] $end
$var wire 1 2# temp $end
$scope module x $end
$var wire 1 +# i0 $end
$var wire 1 3# i1 $end
$var wire 1 2# o $end
$upscope $end
$scope module f $end
$var wire 1 *# a $end
$var wire 1 2# b $end
$var wire 1 (# cin $end
$var wire 1 )# cout $end
$var wire 1 -# sum $end
$upscope $end
$scope module a $end
$var wire 1 *# i0 $end
$var wire 1 +# i1 $end
$var wire 1 .# o $end
$upscope $end
$scope module orr $end
$var wire 1 *# i0 $end
$var wire 1 +# i1 $end
$var wire 1 /# o $end
$upscope $end
$scope module m1 $end
$var wire 1 .# i0 $end
$var wire 1 /# i1 $end
$var wire 1 4# j $end
$var wire 1 0# o $end
$upscope $end
$scope module m2 $end
$var wire 1 -# i0 $end
$var wire 1 0# i1 $end
$var wire 1 5# j $end
$var wire 1 ,# o $end
$upscope $end
$upscope $end
$scope module a14 $end
$var wire 1 6# cin $end
$var wire 1 7# cout $end
$var wire 1 8# i0 $end
$var wire 1 9# i1 $end
$var wire 1 :# o $end
$var wire 1 ;# o1 $end
$var wire 1 <# o2 $end
$var wire 1 =# o3 $end
$var wire 1 ># o4 $end
$var wire 2 ?# op [1:0] $end
$var wire 1 @# temp $end
$scope module x $end
$var wire 1 9# i0 $end
$var wire 1 A# i1 $end
$var wire 1 @# o $end
$upscope $end
$scope module f $end
$var wire 1 8# a $end
$var wire 1 @# b $end
$var wire 1 6# cin $end
$var wire 1 7# cout $end
$var wire 1 ;# sum $end
$upscope $end
$scope module a $end
$var wire 1 8# i0 $end
$var wire 1 9# i1 $end
$var wire 1 <# o $end
$upscope $end
$scope module orr $end
$var wire 1 8# i0 $end
$var wire 1 9# i1 $end
$var wire 1 =# o $end
$upscope $end
$scope module m1 $end
$var wire 1 <# i0 $end
$var wire 1 =# i1 $end
$var wire 1 B# j $end
$var wire 1 ># o $end
$upscope $end
$scope module m2 $end
$var wire 1 ;# i0 $end
$var wire 1 ># i1 $end
$var wire 1 C# j $end
$var wire 1 :# o $end
$upscope $end
$upscope $end
$scope module a15 $end
$var wire 1 D# cin $end
$var wire 1 ! cout $end
$var wire 1 E# i0 $end
$var wire 1 F# i1 $end
$var wire 1 G# o $end
$var wire 1 H# o1 $end
$var wire 1 I# o2 $end
$var wire 1 J# o3 $end
$var wire 1 K# o4 $end
$var wire 2 L# op [1:0] $end
$var wire 1 M# temp $end
$scope module x $end
$var wire 1 F# i0 $end
$var wire 1 N# i1 $end
$var wire 1 M# o $end
$upscope $end
$scope module f $end
$var wire 1 E# a $end
$var wire 1 M# b $end
$var wire 1 D# cin $end
$var wire 1 ! cout $end
$var wire 1 H# sum $end
$upscope $end
$scope module a $end
$var wire 1 E# i0 $end
$var wire 1 F# i1 $end
$var wire 1 I# o $end
$upscope $end
$scope module orr $end
$var wire 1 E# i0 $end
$var wire 1 F# i1 $end
$var wire 1 J# o $end
$upscope $end
$scope module m1 $end
$var wire 1 I# i0 $end
$var wire 1 J# i1 $end
$var wire 1 O# j $end
$var wire 1 K# o $end
$upscope $end
$scope module m2 $end
$var wire 1 H# i0 $end
$var wire 1 K# i1 $end
$var wire 1 P# j $end
$var wire 1 G# o $end
$upscope $end
$upscope $end
$upscope $end
$upscope $end
$enddefinitions $end
#0
$dumpvars
0P#
0O#
0N#
0M#
b0 L#
0K#
0J#
0I#
0H#
0G#
0F#
0E#
0D#
0C#
0B#
0A#
0@#
b0 ?#
0>#
0=#
0<#
0;#
0:#
09#
08#
07#
06#
05#
04#
03#
02#
b0 1#
00#
0/#
0.#
0-#
0,#
0+#
0*#
0)#
0(#
0'#
0&#
0%#
0$#
b0 ##
0"#
0!#
0~"
0}"
0|"
0{"
0z"
0y"
0x"
0w"
0v"
0u"
0t"
b0 s"
0r"
0q"
0p"
0o"
0n"
0m"
0l"
0k"
0j"
0i"
0h"
0g"
0f"
b0 e"
0d"
0c"
0b"
0a"
0`"
0_"
0^"
0]"
0\"
0["
0Z"
0Y"
0X"
b0 W"
0V"
0U"
0T"
0S"
0R"
0Q"
0P"
0O"
0N"
0M"
0L"
0K"
0J"
b0 I"
0H"
0G"
0F"
0E"
0D"
0C"
0B"
0A"
0@"
0?"
0>"
0="
0<"
b0 ;"
0:"
09"
08"
07"
06"
05"
04"
03"
02"
01"
00"
0/"
0."
b0 -"
0,"
0+"
0*"
0)"
0("
0'"
0&"
0%"
0$"
0#"
0""
0!"
0~
b0 }
0|
0{
0z
0y
0x
0w
0v
0u
0t
0s
0r
0q
0p
b0 o
0n
0m
0l
0k
0j
0i
0h
0g
0f
0e
0d
0c
0b
b0 a
0`
0_
0^
0]
0\
0[
0Z
0Y
0X
0W
0V
0U
0T
b0 S
0R
0Q
0P
0O
0N
0M
0L
0K
0J
0I
0H
0G
0F
b0 E
0D
0C
0B
0A
0@
0?
0>
0=
0<
0;
0:
09
08
b0 7
06
05
04
03
02
01
00
0/
0.
b0 -
b0 ,
b0 +
b0 *
b0 )
1(
b0 '
b0 &
b0 %
bx $
0#
b0 "
0!
$end
#50
1#
#60
b0 $
#100
0#
#125
0(
#150
1#
#160
b1 $
#200
0#
#250
1#
#260
1@
1\
1x
16"
1D"
1`"
1|"
1:#
12
1N
1j
1("
1R"
1n"
1,#
1G#
b1111111111111111 "
b1111111111111111 ,
1A
1]
1y
17"
1E"
1a"
1}"
1;#
13
1O
1k
1)"
1S"
1o"
1-#
1H#
15
1Q
1m
1+"
1U"
1q"
1/#
1J#
1F
1C
1b
1_
1~
1{
1<"
19"
1J"
1G"
1f"
1c"
1$#
1!#
1@#
1=#
10
1L
1h
1&"
1P"
1l"
1*#
1E#
1?
1[
1w
15"
1C"
1_"
1{"
19#
b10 $
b1010101001010101 %
b1010101001010101 *
b101010110101010 &
b101010110101010 +
#300
0#
#350
1#
#360
1!
0G#
0H#
1D#
17#
0:#
0;#
16#
1)#
0,#
0-#
1(#
1y"
0|"
0}"
1x"
1k"
0n"
0o"
1j"
1]"
0`"
0a"
1\"
1O"
0R"
0S"
1N"
1A"
0D"
0E"
1@"
13"
06"
07"
12"
1%"
0("
0)"
1$"
1u
0x
0y
1t
1g
0j
0k
1f
1Y
0\
0]
1X
1K
0N
0O
1J
1=
0@
0A
02
b0 "
b0 ,
1<
03
1/
b111111111111111 )
16
18
14
0F
0b
0~
0<"
0J"
0f"
0$#
0@#
1>
1Z
1v
14"
1B"
1^"
1z"
18#
11
0?
0[
0w
05"
0C"
0_"
0{"
09#
b11 $
b1111111111111111 %
b1111111111111111 *
b1 &
b1 +
#400
0#
#450
1#
#460
1G#
b1000000000000000 "
b1000000000000000 ,
0!
1H#
0J#
1F
1T
1b
1p
1~
1."
1<"
1J"
1X"
1f"
1t"
1$#
12#
1@#
0>
0L
0Z
0h
0v
0&"
04"
0B"
0P"
0^"
0l"
0z"
0*#
08#
0E#
1?
1M
1[
1i
1w
1'"
15"
1C"
1Q"
1_"
1m"
1{"
1+#
19#
b100 $
b1 %
b1 *
b111111111111111 &
b111111111111111 +
#500
0#
#550
1#
#560
1D#
17#
0:#
0;#
16#
1)#
0,#
0-#
1(#
1y"
0|"
0}"
1x"
1k"
0n"
0o"
1j"
1]"
0`"
0a"
1\"
1O"
0R"
0S"
1N"
1A"
0D"
0E"
1@"
13"
06"
07"
12"
1%"
0("
0)"
1$"
1u
0x
0y
1t
1g
0j
0k
1f
1Y
0\
0]
1X
1K
0N
0O
1J
1=
0@
0G#
b0 "
b0 ,
1!
0A
0H#
1<
1/
b111111111111111 )
06
1M#
04
05
0C
0Q
0_
0m
0{
0+"
09"
0G"
0U"
0c"
0q"
0!#
0/#
0=#
1.
19
1:
1G
1H
1U
1V
1c
1d
1q
1r
1!"
1""
1/"
10"
1="
1>"
1K"
1L"
1Y"
1Z"
1g"
1h"
1u"
1v"
1%#
1&#
13#
14#
1A#
1B#
1N#
1O#
00
01
0?
0M
0[
0i
0w
0'"
05"
0C"
0Q"
0_"
0m"
0{"
0+#
09#
b101 $
b1 '
b1 -
b1 7
b1 E
b1 S
b1 a
b1 o
b1 }
b1 -"
b1 ;"
b1 I"
b1 W"
b1 e"
b1 s"
b1 ##
b1 1#
b1 ?#
b1 L#
b0 %
b0 *
b0 &
b0 +
#600
0#
#650
1#
#660
0J
0f
0$"
0@"
0N"
0j"
0(#
0D#
1@
0=
1\
0Y
1x
0u
16"
03"
0D"
0A"
1`"
0]"
1|"
0y"
1:#
07#
b10101001010101 )
12
0N
0j
0("
0R"
0n"
0,#
0G#
b101010010101011 "
b101010010101011 ,
1A
1]
1y
17"
0E"
1a"
1}"
1;#
13
16
0O
1R
0k
1n
0)"
1,"
0S"
1V"
0o"
1r"
0-#
10#
0H#
1K#
1D
1`
1|
1:"
1H"
1d"
1"#
1>#
15
1Q
1m
1+"
1U"
1q"
1/#
1J#
0F
1C
0b
1_
0~
1{
0<"
19"
0J"
1G"
0f"
1c"
0$#
1!#
0@#
1=#
10
1L
1h
1&"
1P"
1l"
1*#
1E#
1?
1[
1w
15"
1C"
1_"
1{"
19#
b110 $
b1010101001010101 %
b1010101001010101 *
b101010110101010 &
b101010110101010 +
#700
0#
#750
1#
